{"data":{"name":"Terence Abdullah","gender":"Male","title":"pueblerino","avatar":{"prop":{"AccA":"p00","AccB":"p00","BeastEars":"p00","Body":"p01","Cloak1":"p00","Cloak2":"p00","Clothing2":"p13","Ears":"p01","Eyebrows":"p12","Eyes":"p25","Face":"p01","FacialMark":"p00","FrontHair":"p13","Glasses":"p00","Mouth":"p03","Nose":"p08","RearHair1":"p04","RearHair2":"p04","Tail":"","Wing":"","FrontHair1":"p13","FrontHair2":"p13","Tail1":"","Tail2":"","Wing1":"","Wing2":"","Beard":"p08","Beard1":"p08","Beard2":"p08"},"color":{"AccA":{"c0":"","c1":20,"c2":"","c3":"","c4":"","c5":"","c6":""},"AccB":{"c0":"","c1":"","c2":"","c3":"","c4":"","c5":"","c6":""},"BeastEars":{"c0":"","c1":"","c2":"","c3":"","c4":"","c5":"","c6":""},"Body":{"c0":"","c1":38,"c2":21,"c3":"","c4":"","c5":"","c6":""},"Cloak1":{"c0":"","c1":"","c2":"","c3":"","c4":"","c5":"","c6":""},"Cloak2":{"c0":"","c1":"","c2":"","c3":"","c4":"","c5":"","c6":""},"Clothing2":{"c0":"","c1":"","c2":"","c3":72,"c4":62,"c5":"","c6":""},"Ears":{"c0":"","c1":38,"c2":21,"c3":"","c4":"","c5":"","c6":""},"Eyebrows":{"c0":"","c1":92,"c2":86,"c3":"","c4":"","c5":"","c6":""},"Eyes":{"c0":"","c1":0,"c2":0,"c3":"","c4":"","c5":"","c6":""},"Face":{"c0":"","c1":38,"c2":21,"c3":"","c4":"","c5":"","c6":""},"FacialMark":{"c0":"","c1":"","c2":"","c3":"","c4":"","c5":"","c6":""},"FrontHair":{"c0":"","c1":92,"c2":86,"c3":"","c4":"","c5":"","c6":""},"Glasses":{"c0":"","c1":"","c2":"","c3":"","c4":"","c5":"","c6":""},"Mouth":{"c0":"","c1":38,"c2":21,"c3":"","c4":"","c5":"","c6":""},"Nose":{"c0":"","c1":38,"c2":21,"c3":"","c4":"","c5":"","c6":""},"RearHair1":{"c0":"","c1":92,"c2":86,"c3":"","c4":"","c5":"","c6":""},"RearHair2":{"c0":"","c1":92,"c2":86,"c3":"","c4":"","c5":"","c6":""},"Tail":{"c0":"","c1":"","c2":"","c3":"","c4":"","c5":"","c6":""},"Wing":{"c0":"","c1":"","c2":"","c3":"","c4":"","c5":"","c6":""},"FrontHair1":{"c0":"","c1":92,"c2":86,"c3":"","c4":"","c5":"","c6":""},"FrontHair2":{"c0":"","c1":92,"c2":86,"c3":"","c4":"","c5":"","c6":""},"Tail1":{"c0":"","c1":"","c2":"","c3":"","c4":"","c5":"","c6":""},"Tail2":{"c0":"","c1":"","c2":"","c3":"","c4":"","c5":"","c6":""},"Wing1":{"c0":"","c1":"","c2":"","c3":"","c4":"","c5":"","c6":""},"Wing2":{"c0":"","c1":"","c2":"","c3":"","c4":"","c5":"","c6":""},"Beard":{"c1":92,"c2":"","c3":"","c4":"","c5":"","c6":""},"Beard1":{"c1":104,"c2":"","c3":"","c4":"","c5":"","c6":""},"Beard2":{"c1":104,"c2":"","c3":"","c4":"","c5":"","c6":""}},"required":["Body","Eyes","Face","Mouth","Nose","Ears"],"canvas":["canvas_face","canvas_facehappy","canvas_sv","canvas_tv","canvas_tvd"],"gender":"Female","groupFace":["Body","Face","Ears","Nose","Mouth"],"groupHair":["RearHair2","RearHair1","Eyebrows","FrontHair"]}}}